safe_backup/__init__.py
safe_backup/_version.py
safe_backup/safe_backup.py
safe_backup-0.1.5.dist-info/LICENSE
safe_backup-0.1.5.dist-info/METADATA
safe_backup-0.1.5.dist-info/WHEEL
safe_backup-0.1.5.dist-info/entry_points.txt
safe_backup-0.1.5.dist-info/top_level.txt
safe_backup-0.1.5.dist-info/RECORD
