Metadata-Version: 2.1
Name: safe_backup
Version: 0.1.5
Summary: This program creates a secure backup of your files from a specified directory or an object storage location.
Author-email: Vahidreza Naderi <vahidrnaderi@gmail.com>
Maintainer-email: Vahidreza Naderi <vahidrnaderi@gmail.com>
License: Apache License
Project-URL: Repository, https://github.com/vahidrnaderi/safe_backup
Keywords: safe,backup,safebackup,safe_backup,safe backup,safe-backup,copy,safe copy,s3,s3 copy,s3 backup
Requires-Python: >=3.10
License-File: LICENSE
Requires-Dist: async-timeout ==4.0.3
Requires-Dist: boto3 ==1.28.62
Requires-Dist: botocore ==1.31.62
Requires-Dist: certifi ==2023.7.22
Requires-Dist: jmespath ==1.0.1
Requires-Dist: minio ==7.1.17
Requires-Dist: python-dateutil ==2.8.2
Requires-Dist: redis ==5.0.0
Requires-Dist: s3transfer ==0.7.0
Requires-Dist: six ==1.16.0
Requires-Dist: urllib3 ==2.0.5
